README
setup.py
ipycon/__init__.py
ipycon.egg-info/PKG-INFO
ipycon.egg-info/SOURCES.txt
ipycon.egg-info/dependency_links.txt
ipycon.egg-info/not-zip-safe
ipycon.egg-info/requires.txt
ipycon.egg-info/top_level.txt
ipycon/database/GetQuery.py
ipycon/database/ImportQuery.py
ipycon/database/__init__.py
ipycon/manufacture/Lot.py
ipycon/manufacture/__init__.py
ipycon/manufacture/lot.py
ipycon/math/Geometry.py
ipycon/math/__init__.py
ipycon/sample/__init__.py
ipycon/sample/sample.py
ipycon/statsmod/Geometry.py
ipycon/statsmod/HypoTests.py
ipycon/statsmod/__init__.py
ipycon/statsmod/vif.py
ipycon/tests/__init__.py
ipycon/tests/test.py